fvupgrader.py
fvupgrader-1.0.9.dist-info/METADATA
fvupgrader-1.0.9.dist-info/WHEEL
fvupgrader-1.0.9.dist-info/entry_points.txt
fvupgrader-1.0.9.dist-info/RECORD
