Metadata-Version: 2.1
Name: fvupgrader
Version: 1.0.9
Summary: fvupgrader streamlines version upgrades in Flutter projects by automatically updating the pubspec.yaml file and tagging changes in Git. Simplify version control for your Flutter apps, packages, and plugins with this versatile tool.
License: MIT
Author: Emilio Dalla Torre
Author-email: info@emiliodallatorre.it
Requires-Python: >=3.9,<4.0
Classifier: License :: OSI Approved :: MIT License
Classifier: Programming Language :: Python :: 3
Classifier: Programming Language :: Python :: 3.9
Classifier: Programming Language :: Python :: 3.10
Classifier: Programming Language :: Python :: 3.11
Classifier: Programming Language :: Python :: 3.12
